augint_billing_lib/__init__.py
augint_billing_lib/adapters/apigw_admin.py
augint_billing_lib/adapters/apigw_usage.py
augint_billing_lib/adapters/cognito.py
augint_billing_lib/adapters/ddb_audit.py
augint_billing_lib/adapters/ddb_repo.py
augint_billing_lib/adapters/stripe.py
augint_billing_lib/bootstrap.py
augint_billing_lib/cli/__init__.py
augint_billing_lib/cli/__main__.py
augint_billing_lib/cli/admin/__init__.py
augint_billing_lib/cli/aws/__init__.py
augint_billing_lib/cli/aws/apigateway_ops.py
augint_billing_lib/cli/aws/cloudwatch_ops.py
augint_billing_lib/cli/aws/eventbridge_ops.py
augint_billing_lib/cli/aws/lambda_ops.py
augint_billing_lib/cli/billing/__init__.py
augint_billing_lib/cli/billing/env.py
augint_billing_lib/cli/billing/process.py
augint_billing_lib/cli/billing/sync.py
augint_billing_lib/cli/config.py
augint_billing_lib/cli/infra/__init__.py
augint_billing_lib/cli/infra/attach.py
augint_billing_lib/cli/infra/detach.py
augint_billing_lib/cli/infra/list.py
augint_billing_lib/cli/infra/pause.py
augint_billing_lib/cli/infra/resume.py
augint_billing_lib/cli/infra/status.py
augint_billing_lib/cli/infra/trigger.py
augint_billing_lib/cli/infra/verify.py
augint_billing_lib/cli/monitor/__init__.py
augint_billing_lib/cli/monitor/dashboard.py
augint_billing_lib/cli/products/__init__.py
augint_billing_lib/cli/products/diagnose.py
augint_billing_lib/cli/products/list_products.py
augint_billing_lib/cli/products/setup.py
augint_billing_lib/cli/products/show.py
augint_billing_lib/cli/products/verify.py
augint_billing_lib/cli/report/__init__.py
augint_billing_lib/cli/setup/__init__.py
augint_billing_lib/cli/setup/activate_eventbus.py
augint_billing_lib/cli/setup/eventbridge.py
augint_billing_lib/cli/setup/stripe_product.py
augint_billing_lib/cli/setup/verify.py
augint_billing_lib/cli/test/__init__.py
augint_billing_lib/cli/test/integration/__init__.py
augint_billing_lib/cli/test/integration/cycle.py
augint_billing_lib/cli/test/integration/link.py
augint_billing_lib-3.10.1.dist-info/LICENSE
augint_billing_lib-3.10.1.dist-info/METADATA
augint_billing_lib-3.10.1.dist-info/WHEEL
augint_billing_lib-3.10.1.dist-info/entry_points.txt
augint_billing_lib-3.10.1.dist-info/RECORD
