Metadata-Version: 2.3
Name: augint-billing-lib
Version: 3.10.1
Summary: Billing service library for API usage tracking and Stripe integration.
License: Copyright (c) 2024 Augmenting Integrations LLC
Author: Samuel Vange
Author-email: 7166607+svange@users.noreply.github.com
Requires-Python: >=3.12,<4.0
Classifier: License :: Other/Proprietary License
Classifier: Programming Language :: Python :: 3
Classifier: Programming Language :: Python :: 3.12
Classifier: Programming Language :: Python :: 3.13
Requires-Dist: boto3 (>=1.39.0,<2.0.0)
Requires-Dist: boto3-stubs[apigateway,cognito-idp,dynamodb] (>=1.40.16,<2.0.0)
Requires-Dist: click (>=8.1.0,<8.2.0)
Requires-Dist: pydantic (>=2.0.0,<3.0.0)
Requires-Dist: pydantic-settings (>=2.0.0,<3.0.0)
Requires-Dist: python-dotenv (>=1.0.0,<2.0.0)
Requires-Dist: stripe (>=12.0.0,<13.0.0)
Requires-Dist: toml (>=0.10.0,<1.0.0)
